hanzi_chaizi/__init__.py
hanzi_chaizi/hanzi_chaizi.py
hanzi_chaizi/data/data.pkl
hanzi_chaizi-0.4.0.dist-info/METADATA
hanzi_chaizi-0.4.0.dist-info/WHEEL
hanzi_chaizi-0.4.0.dist-info/licenses/LICENSE
hanzi_chaizi-0.4.0.dist-info/RECORD
