Metadata-Version: 2.4
Name: hanzi_chaizi
Version: 0.4.0
Summary: Chinese character decomposition tools for breaking down characters into basic structural units
Project-URL: Homepage, https://github.com/howl-anderson/hanzi_chaizi
Project-URL: Repository, https://github.com/howl-anderson/hanzi_chaizi
Project-URL: Issues, https://github.com/howl-anderson/hanzi_chaizi/issues
Author-email: Xiaoquan Kong <u1mail2me@gmail.com>
License-Expression: Apache-2.0
License-File: LICENSE
Keywords: character-decomposition,chinese,deep-learning,hanzi,nlp
Requires-Python: >=3.10
Provides-Extra: dev
Requires-Dist: pytest; extra == 'dev'
